{
  "id": "44fc5e89d31c8b92",
  "slug": "voenen-samolet-dete-germany-lecenie-44fc",
  "headline": "Военен самолет превози дете за спешно лечение в Германия",
  "meta_description": "Военен самолет Спартан успешно транспортира болно дете от София до Щутгарт за необходимото медицинско лечение.",
  "summary_short": "Военна авиация превози дете за критично лечение в Германия, показвайки доброволчество и отговорност при спешни медицински случаи.",
  "body": "В едно сложно и чувствително на човека решение, Министерството на отбраната отпусна военен самолет да помогне на болно дете. Полетът от София до Щутгарт се осъществи ранна сутрин, демонстрирайки готовността на държавните институции да подпомагат отчаяни семейства.\n\nТакива действия напомнят, че дори в политически раздели времена държавата остава защитница на най-уязвимите си граждани. Детето получи възможност да стигне до специализирано германско медицинско учреждение благодарение на пълнота и бързина.",
  "category": "zdrave",
  "tags": [
    "здраве",
    "деца",
    "помощ",
    "международна-сътрудничество"
  ],
  "source_name": "Дневник",
  "source_url": "https://www.dnevnik.bg/zdrave/2026/07/07/4933282_voenen_samolet_spartan_prevozi_dete_za_lechenie_v/?ref=rss",
  "published": "2026-07-07T17:02:01Z",
  "lang": "bg"
}